memex/__init__.py
memex/__main__.py
memex/_logging.py
memex/backlinks_cache.py
memex/batch.py
memex/beads_client.py
memex/cli.py
memex/config.py
memex/context.py
memex/core.py
memex/errors.py
memex/evaluation.py
memex/frontmatter.py
memex/health_cache.py
memex/models.py
memex/patch.py
memex/search_history.py
memex/server.py
memex/session.py
memex/tags_cache.py
memex/templates.py
memex/views_tracker.py
memex/indexer/__init__.py
memex/indexer/chroma_index.py
memex/indexer/hybrid.py
memex/indexer/manifest.py
memex/indexer/watcher.py
memex/indexer/whoosh_index.py
memex/parser/__init__.py
memex/parser/links.py
memex/parser/markdown.py
memex/parser/md_renderer.py
memex/parser/title_index.py
memex/publisher/__init__.py
memex/publisher/generator.py
memex/publisher/renderer.py
memex/publisher/search_index.py
memex/publisher/templates.py
memex/publisher/theme/search.js
memex/publisher/theme/sidebar.js
memex/publisher/theme/style.css
memex/webapp/__init__.py
memex/webapp/api.py
memex/webapp/events.py
memex/webapp/static/index.html
memex_kb-0.1.1.dist-info/METADATA
memex_kb-0.1.1.dist-info/WHEEL
memex_kb-0.1.1.dist-info/entry_points.txt
memex_kb-0.1.1.dist-info/licenses/LICENSE
memex_kb-0.1.1.dist-info/RECORD
