Metadata-Version: 2.4
Name: memex-kb
Version: 0.1.1
Summary: Personal knowledge base with semantic search
Project-URL: Homepage, https://github.com/voidlabs/memex
Project-URL: Documentation, https://github.com/voidlabs/memex#readme
Project-URL: Repository, https://github.com/voidlabs/memex
Project-URL: Issues, https://github.com/voidlabs/memex/issues
Author: Void Labs
License-Expression: MIT
License-File: LICENSE
Keywords: embeddings,knowledge-base,mcp,personal-wiki,semantic-search
Classifier: Development Status :: 4 - Beta
Classifier: Environment :: Console
Classifier: Intended Audience :: Developers
Classifier: License :: OSI Approved :: MIT License
Classifier: Operating System :: OS Independent
Classifier: Programming Language :: Python :: 3
Classifier: Programming Language :: Python :: 3.11
Classifier: Programming Language :: Python :: 3.12
Classifier: Topic :: Documentation
Classifier: Topic :: Text Processing :: Markup :: Markdown
Requires-Python: >=3.11
Requires-Dist: click>=8.1.0
Requires-Dist: fastapi>=0.115.0
Requires-Dist: fastmcp>=2.14.1
Requires-Dist: jinja2>=3.1.0
Requires-Dist: pydantic>=2.12.0
Requires-Dist: python-frontmatter>=1.1.0
Requires-Dist: tiktoken>=0.5.0
Requires-Dist: uvicorn>=0.32.0
Requires-Dist: watchdog>=4.0.0
Requires-Dist: whoosh-reloaded>=2.7.4
Provides-Extra: semantic
Requires-Dist: chromadb<1.0.0,>=0.5.0; extra == 'semantic'
Requires-Dist: posthog<5.0.0; extra == 'semantic'
Requires-Dist: sentence-transformers>=3.0.0; extra == 'semantic'
Requires-Dist: torch>=2.0.0; extra == 'semantic'
